{
    "name": "모라도나무 🌐",
    "category": "patchouli:trees",
    "icon": "atmospheric:morado_sapling",
    "pages": [
        {
            "type": "patchouli:text",
            "text": "$(l)정보$()$(li)🌐 §5연중§r$(li)크기: 1x1"
        },
        {
            "type": "patchouli:multiblock",
            "name ": "모라도나무",
            "enable_visualize": false,
            "multiblock": {
                "pattern": [
                    [
                        "         ",
                        "      L  ",
                        "     lLl ",
                        "      l  ",
                        "         ",
                        "         ",
                        "         ",
                        "         "
                    ],
                    [
                        "     lll ",
                        "    lLlll",
                        "    llWLl",
                        "    lLLll",
                        "     lll ",
                        "         ",
                        "         ",
                        "         "
                    ],
                    [
                        "         ",
                        "         ",
                        "  lll W  ",
                        " LlLll   ",
                        " LLlll   ",
                        " lLLll   ",
                        "  lll    ",
                        "         "
                    ],
                    [
                        "         ",
                        "         ",
                        " LlLlL   ",
                        "lllLLWT  ",
                        "LllWlll  ",
                        "lllllll  ",
                        "llLllll  ",
                        " lllll   "
                    ],
                    [
                        "         ",
                        "         ",
                        "         ",
                        "    WT   ",
                        "   W     ",
                        "         ",
                        "         ",
                        "         "
                    ],
                    [
                        "         ",
                        "         ",
                        "         ",
                        "    W    ",
                        "   W     ",
                        "         ",
                        "         ",
                        "         "
                    ],
                    [
                        "         ",
                        "         ",
                        "         ",
                        "   WT    ",
                        "   t     ",
                        "         ",
                        "         ",
                        "         "
                    ],
                    [
                        "         ",
                        "         ",
                        "         ",
                        "   W     ",
                        "         ",
                        "         ",
                        "         ",
                        "         "
                    ],
                    [
                        "         ",
                        "         ",
                        "         ",
                        "   W0    ",
                        "         ",
                        "         ",
                        "         ",
                        "         "
                    ]
                ],
                "mapping": {
                    "0": "minecraft:air",
                    "l": "atmospheric:flowering_morado_leaves",
                    "L": "atmospheric:morado_leaves",
                    "W": "atmospheric:morado_log[axis=y]",
                    "T": "atmospheric:morado_log[axis=z]",
                    "t": "atmospheric:morado_log[axis=x]"
                }
            }
        }
    ]
}